setup.py
mailclient/__init__.py
mailclient/mail_exceptions.py
mailclient/message.py
mailclient/server.py
mailclient/tests.py
mailclient.egg-info/PKG-INFO
mailclient.egg-info/SOURCES.txt
mailclient.egg-info/dependency_links.txt
mailclient.egg-info/not-zip-safe
mailclient.egg-info/requires.txt
mailclient.egg-info/top_level.txt